autopx/__init__.py
autopx/config/__init__.py
autopx/core/__init__.py
autopx/core/autopx.py
autopx/core/data_analysis.py
autopx/core/decision_engine.py
autopx/fallback/__init__.py
autopx/fallback/fallback_manager.py
autopx/fallback/fallback_rules.py
autopx/preprocessing/__init__.py
autopx/preprocessing/cleaner.py
autopx/preprocessing/new_demo.py
autopx/preprocessing/sequence_handler.py
autopx/preprocessing/stopwords.py
autopx/preprocessing/tokenizer.py
autopx/reports/__init__.py
autopx/reports/json_report.py
autopx/reports/markdown_report.py
autopx/reports/pdf_report.py
autopx/reports/report_builder.py
autopx/utils/__init__.py
autopx/utils/constants.py
autopx/utils/helpers.py
autopx/utils/logger.py
autopx/vectorizers/__init__.py
autopx/vectorizers/count.py
autopx/vectorizers/embeddings.py
autopx/vectorizers/tfidf.py
autopx-1.1.0.dist-info/licenses/LICENSE
autopx-1.1.0.dist-info/METADATA
autopx-1.1.0.dist-info/WHEEL
autopx-1.1.0.dist-info/top_level.txt
autopx-1.1.0.dist-info/RECORD
