Metadata-Version: 2.4
Name: AutoPX
Version: 1.1.0
Summary: AutoPX – Automatic NLP Preprocessing with Explainable Reports
Home-page: https://github.com/MudassarGill/AutoPX
Author: Mudassar Hussain
Author-email: mudassarjutt65030@gmail.com
Classifier: Programming Language :: Python :: 3
Classifier: License :: OSI Approved :: MIT License
Classifier: Operating System :: OS Independent
Classifier: Topic :: Text Processing :: Linguistic
Classifier: Intended Audience :: Developers
Requires-Python: >=3.8
License-File: LICENSE
Requires-Dist: pandas
Requires-Dist: numpy
Requires-Dist: scikit-learn
Requires-Dist: tensorflow
Requires-Dist: deepface
Requires-Dist: reportlab
Dynamic: author
Dynamic: author-email
Dynamic: classifier
Dynamic: description
Dynamic: description-content-type
Dynamic: home-page
Dynamic: license-file
Dynamic: requires-dist
Dynamic: requires-python
Dynamic: summary
